client/__init__.py
client/_compat.py
client/argparser.py
client/configuration.py
client/meta.py
client/multipart.py
client/resource.py
client/session.py
client/util.py
client/certs/corelight.pem
corelight_client-1.5.17.data/scripts/bro-pkg-bundle
corelight_client-1.5.17.data/scripts/brobox
corelight_client-1.5.17.data/scripts/corelight-client
corelight_client-1.5.17.dist-info/licenses/COPYING
corelight_client-1.5.17.dist-info/licenses/LICENSE-APACHE
corelight_client-1.5.17.dist-info/licenses/NOTICE
corelight_client-1.5.17.dist-info/METADATA
corelight_client-1.5.17.dist-info/WHEEL
corelight_client-1.5.17.dist-info/top_level.txt
corelight_client-1.5.17.dist-info/RECORD
