Metadata-Version: 2.4
Name: corelight-client
Version: 1.5.17
Summary: Corelight API client
Home-page: https://github.com/corelight/corelight-client
Author: Corelight
Author-email: info@corelight.com
License: BSD
Classifier: License :: OSI Approved :: BSD License
Classifier: Programming Language :: Python :: 3 :: Only
Obsoletes: brobox_client
License-File: LICENSE-APACHE
License-File: COPYING
License-File: NOTICE
Requires-Dist: requests!=2.17.1,!=2.17.2,<2.30.0,>=2.9.1
Dynamic: author
Dynamic: author-email
Dynamic: classifier
Dynamic: description
Dynamic: home-page
Dynamic: license
Dynamic: license-file
Dynamic: obsoletes
Dynamic: requires-dist
Dynamic: summary
